RPGtext/__init__.py
RPG_text_engine-0.1.2.dist-info/LICENCE.txt
RPG_text_engine-0.1.2.dist-info/METADATA
RPG_text_engine-0.1.2.dist-info/WHEEL
RPG_text_engine-0.1.2.dist-info/top_level.txt
RPG_text_engine-0.1.2.dist-info/RECORD
